[
  { "name": "주연진", "phone": "010-6886-8615", "pass": 1 },
  { "name": "방혜진", "phone": "010-3509-7243", "pass": 1 },
  { "name": "정민지", "phone": "010-5039-6958", "pass": 1 },
  { "name": "권지민", "phone": "010-2260-0952", "pass": 1 },
  { "name": "홍민우", "phone": "010-8947-0574", "pass": 1 },
  { "name": "박주희", "phone": "010-2371-0240", "pass": 1 },
  { "name": "김소영", "phone": "010-9150-5193", "pass": 1 },
  { "name": "이세민", "phone": "010-3666-9401", "pass": 1 },
  { "name": "김서진", "phone": "010-8406-8995", "pass": 1 },
  { "name": "오승연", "phone": "010-5824-9132", "pass": 1 },
  { "name": "박소정", "phone": "010-5616-7839", "pass": 1 },
  { "name": "유새연", "phone": "010-2506-4380", "pass": 1 },
  { "name": "장우림", "phone": "010-2826-0638", "pass": 1 },
  { "name": "노소은", "phone": "010-5675-7747", "pass": 1 },
  { "name": "홍성주", "phone": "010-7921-2330", "pass": 1 },
  { "name": "주현정", "phone": "010-8345-8242", "pass": 1 },
  { "name": "이채연", "phone": "010-9902-4075", "pass": 1 },
  { "name": "고유민", "phone": "010-9286-5939", "pass": 1 },
  { "name": "한윤이", "phone": "010-2853-6271", "pass": 0 },
  { "name": "한지영", "phone": "010-5871-2230", "pass": 0 },
  { "name": "김하늘", "phone": "010-4117-8482", "pass": 0 },
  { "name": "권민정", "phone": "010-3487-3530", "pass": 0 },
  { "name": "이어진", "phone": "010-7115-1436", "pass": 0 },
  { "name": "오혜인", "phone": "010-2685-6919", "pass": 0 },
  { "name": "우수정", "phone": "010-9100-1249", "pass": 0 },
  { "name": "배지완", "phone": "010-9980-8630", "pass": 0 },
  { "name": "변서영", "phone": "010-3157-2181", "pass": 0 },
  { "name": "강도경", "phone": "010-3039-2537", "pass": 0 },
  { "name": "손다현", "phone": "010-5925-3776", "pass": 0 },
  { "name": "이혜정", "phone": "010-2385-0981", "pass": 0 },
  { "name": "노혜경", "phone": "010-9140-6763", "pass": 0 },
  { "name": "이혜연", "phone": "010-4456-7915", "pass": 0 },
  { "name": "류소연", "phone": "010-9942-2248", "pass": 0 },
  { "name": "김서인", "phone": "010-5235-1389", "pass": 0 },
  { "name": "김현수", "phone": "010-4079-0778", "pass": 0 },
  { "name": "김연수", "phone": "010-2873-6898", "pass": 0 },
  { "name": "김세원", "phone": "010-8418-6889", "pass": 0 },
  { "name": "남지연", "phone": "010-2662-5447", "pass": 0 },
  { "name": "한혜진", "phone": "010-4037-4720", "pass": 0 },
  { "name": "손채연", "phone": "010-3881-0803", "pass": 0 },
  { "name": "류주아", "phone": "010-7495-2795", "pass": 0 },
  { "name": "손예슬", "phone": "010-9723-3722", "pass": 0 },
  { "name": "이도현", "phone": "010-8894-8022", "pass": 0 },
  { "name": "한민주", "phone": "010-6609-5360", "pass": 0 },
  { "name": "이지우", "phone": "010-2038-6103", "pass": 0 },
  { "name": "허민영", "phone": "010-4799-5438", "pass": 0 },
  { "name": "한현서", "phone": "010-4920-2861", "pass": 3 }
]
